texttoaudio/__init__.py
texttoaudio/texttoaudio.py
texttoaudioconverter28-0.1.dist-info/METADATA
texttoaudioconverter28-0.1.dist-info/WHEEL
texttoaudioconverter28-0.1.dist-info/top_level.txt
texttoaudioconverter28-0.1.dist-info/RECORD
